psola/__init__.py
psola/__main__.py
psola/core.py
psola-0.0.1.dist-info/LICENSE
psola-0.0.1.dist-info/METADATA
psola-0.0.1.dist-info/WHEEL
psola-0.0.1.dist-info/top_level.txt
psola-0.0.1.dist-info/RECORD
