Metadata-Version: 2.1
Name: psola
Version: 0.0.1
Summary: Time-domain pitch-synchronous overlap-add
Home-page: https://github.com/maxrmorrison/psola
Author: Max Morrison
Author-email: maxrmorrison@gmail.com
License: GPLv3
Keywords: audio,duration,pitch,speech,stretch,vocode
Platform: UNKNOWN
